sb_utils/__init__.py
sb_utils-0.1.1.dist-info/METADATA
sb_utils-0.1.1.dist-info/WHEEL
sb_utils-0.1.1.dist-info/RECORD
