Metadata-Version: 2.1
Name: sb_utils
Version: 0.1.1
Summary: A collection of framework specific utilities for working with Supabase.
License: MIT
Author: Basri
Author-email: h@basri.me
Requires-Python: >=3.12,<4.0
Classifier: License :: OSI Approved :: MIT License
Classifier: Programming Language :: Python :: 3
Classifier: Programming Language :: Python :: 3.12
Requires-Dist: pydantic (>=2.7.1,<3.0.0)
Requires-Dist: supabase (>=2.4.3,<3.0.0)
